{
  "id": "gs-211",
  "来源": "古筮真诠·第十三章",
  "问题": "病",
  "时间": "卯月甲申日",
  "旬空": "未详",
  "本卦": "地山谦",
  "变卦": "水山蹇",
  "世应": "未详",
  "动爻": "未详",
  "日月建": "卯月甲申日",
  "六冲": false,
  "作者": "朱辰彬",
  "断语": "向的核心信息，动而生克冲合、动而化进化退、动而化绝化破、动而回头生克、动而 变化出用忌之神等等，一切祸福定性尽在其中。这就是我要向读者们展示的吉凶定性 全新定义，它在理论上彻底颠覆了自古分析以日、月、动、变 机械等量对比的固有套",
  "用神": "子孙爻",
  "断语吉凶": "凶",
  "原文关键分析": "向的核心信息，动而生克冲合、动而化进化退、动而化绝化破、动而回头生克、动而 变化出用忌之神等等，一切祸福定性尽在其中。这就是我要向读者们展示的吉凶定性 全新定义，它在理论上彻底颠覆了自古分析以日、月、动、变 机械等量对比的固有套",
  "应期": "未详",
  "验证点": [
    "用神选取"
  ]
}